pyerp/__init__.py
pyerp/analysis/__init__.py
pyerp/analysis/erp.py
pyerp/analysis/raw.py
pyerp/analysis/utils.py
pyerp/classification/__init__.py
pyerp/classification/bci.py
pyerp/classification/classification.py
pyerp/classification/metrices.py
pyerp/classification/utils.py
pyerp/utils/__init__.py
pyerp/utils/analysis.py
pyerp/utils/mne.py
pyerp/utils/std.py
pyerp/utils/pd/__init__.py
pyerp/utils/pd/pd.py
pyerp/visualization/__init__.py
pyerp/visualization/erp.py
pyerp/visualization/visualization.py
pyerp-0.0.4.dist-info/LICENSE
pyerp-0.0.4.dist-info/METADATA
pyerp-0.0.4.dist-info/WHEEL
pyerp-0.0.4.dist-info/top_level.txt
pyerp-0.0.4.dist-info/RECORD
