Metadata-Version: 2.1
Name: pyerp
Version: 0.0.4
Summary: python library for Event-Related Potentials (ERPs) analysis
Home-page: https://github.com/simonkojima/pyerp
Author: Simon Kojima
Author-email: simon.kojima@outlook.com
Project-URL: Bug Tracker, https://github.com/simonkojima/pyerp/issues
Classifier: Programming Language :: Python :: 3
Classifier: License :: OSI Approved :: MIT License
Classifier: Operating System :: OS Independent
Requires-Python: >=3.6
License-File: LICENSE
Requires-Dist: numpy
Requires-Dist: mne
Requires-Dist: sklearn
